LICENSE
MANIFEST.in
README
setup.cfg
setup.py
seqansphinx/__init__.py
seqansphinx/doxlinks.py
seqansphinx/includefrags.py
seqansphinx.egg-info/PKG-INFO
seqansphinx.egg-info/SOURCES.txt
seqansphinx.egg-info/dependency_links.txt
seqansphinx.egg-info/namespace_packages.txt
seqansphinx.egg-info/not-zip-safe
seqansphinx.egg-info/requires.txt
seqansphinx.egg-info/top_level.txt