Metadata-Version: 1.1
Name: seqansphinx
Version: 0.3.0
Summary: Sphinx extension for SeqAn Sphinx document
Home-page: http://github.com/seqan/seqan-sphinx
Author: Manuel Holtgrewe
Author-email: manuel.holtgrewe@fu-berlin.de
License: MIT
Download-URL: http://pypi.python.org/pypi/seqansphinx
Platform: any
Classifier: Development Status :: 4 - Beta
Classifier: Environment :: Console
Classifier: Environment :: Web Environment
Classifier: Intended Audience :: Developers
Classifier: License :: OSI Approved :: BSD License
Classifier: Operating System :: OS Independent
Classifier: Programming Language :: Python
Classifier: Topic :: Documentation
Classifier: Topic :: Utilities
